pyplotgui-1.0.0.dist-info/RECORD
pyplotgui-1.0.0.dist-info/LICENSE
pyplotgui-1.0.0.dist-info/WHEEL
pyplotgui-1.0.0.dist-info/top_level.txt
pyplotgui-1.0.0.dist-info/METADATA
imgui/extra.py
imgui/plot.cpp
imgui/internal.h
imgui/core.h
imgui/plot.h
imgui/core.pxd
imgui/core.cpp
imgui/internal.pyx
imgui/plot.cpython-38-darwin.so
imgui/internal.cpython-38-darwin.so
imgui/cimplot.pxd
imgui/__init__.py
imgui/enums.pxd
imgui/enums_internal.pxd
imgui/internal.cpp
imgui/cimgui.pxd
imgui/internal.pxd
imgui/ansifeed.pxd
imgui/core.cpython-38-darwin.so
imgui/_compat.py
imgui/core.pyx
imgui/common.pyx
imgui/plot.pyx
imgui/integrations/glumpy.py
imgui/integrations/sdl2.py
imgui/integrations/__init__.py
imgui/integrations/opengl.py
imgui/integrations/pygame.py
imgui/integrations/cocos2d.py
imgui/integrations/pyglet.py
imgui/integrations/base.py
imgui/integrations/glfw.py
